{"sprites":[{"x":75,"y":0,"w":60,"h":75,"type":"tree"},{"x":150,"y":0,"w":60,"h":75,"type":"tree"},{"x":225,"y":0,"w":60,"h":75,"type":"tree"},{"x":300,"y":0,"w":60,"h":75,"type":"tree"},{"x":375,"y":0,"w":60,"h":75,"type":"tree"},{"x":450,"y":0,"w":60,"h":75,"type":"tree"},{"x":525,"y":0,"w":60,"h":75,"type":"tree"},{"x":600,"y":0,"w":60,"h":75,"type":"tree"},{"x":675,"y":0,"w":60,"h":75,"type":"tree"},{"x":675,"y":75,"w":60,"h":75,"type":"tree"},{"x":675,"y":150,"w":60,"h":75,"type":"tree"},{"x":675,"y":300,"w":60,"h":75,"type":"tree"},{"x":675,"y":375,"w":60,"h":75,"type":"tree"},{"x":600,"y":450,"w":60,"h":75,"type":"tree"},{"x":675,"y":450,"w":60,"h":75,"type":"tree"},{"x":525,"y":450,"w":60,"h":75,"type":"tree"},{"x":450,"y":450,"w":60,"h":75,"type":"tree"},{"x":375,"y":450,"w":60,"h":75,"type":"tree"},{"x":225,"y":450,"w":60,"h":75,"type":"tree"},{"x":150,"y":450,"w":60,"h":75,"type":"tree"},{"x":75,"y":450,"w":60,"h":75,"type":"tree"},{"x":0,"y":375,"w":60,"h":75,"type":"tree"},{"x":0,"y":450,"w":60,"h":75,"type":"tree"},{"x":0,"y":300,"w":60,"h":75,"type":"tree"},{"x":0,"y":225,"w":60,"h":75,"type":"tree"},{"x":0,"y":150,"w":60,"h":75,"type":"tree"},{"x":0,"y":75,"w":60,"h":75,"type":"tree"},{"x":75,"y":300,"w":60,"h":75,"type":"tree"},{"x":150,"y":300,"w":60,"h":75,"type":"tree"},{"x":150,"y":225,"w":60,"h":75,"type":"tree"},{"x":600,"y":150,"w":60,"h":75,"type":"tree"},{"x":525,"y":150,"w":60,"h":75,"type":"tree"},{"x":675,"y":525,"w":60,"h":75,"type":"tree"},{"x":600,"y":600,"w":60,"h":75,"type":"tree"},{"x":675,"y":600,"w":60,"h":75,"type":"tree"},{"x":675,"y":750,"w":60,"h":75,"type":"tree"},{"x":675,"y":825,"w":60,"h":75,"type":"tree"},{"x":600,"y":900,"w":60,"h":75,"type":"tree"},{"x":675,"y":900,"w":60,"h":75,"type":"tree"},{"x":525,"y":900,"w":60,"h":75,"type":"tree"},{"x":450,"y":900,"w":60,"h":75,"type":"tree"},{"x":375,"y":900,"w":60,"h":75,"type":"tree"},{"x":300,"y":900,"w":60,"h":75,"type":"tree"},{"x":225,"y":900,"w":60,"h":75,"type":"tree"},{"x":150,"y":900,"w":60,"h":75,"type":"tree"},{"x":75,"y":900,"w":60,"h":75,"type":"tree"},{"x":0,"y":900,"w":60,"h":75,"type":"tree"},{"x":0,"y":825,"w":60,"h":75,"type":"tree"},{"x":0,"y":750,"w":60,"h":75,"type":"tree"},{"x":0,"y":675,"w":60,"h":75,"type":"tree"},{"x":0,"y":600,"w":60,"h":75,"type":"tree"},{"x":75,"y":750,"w":60,"h":75,"type":"tree"},{"x":150,"y":750,"w":60,"h":75,"type":"tree"},{"x":225,"y":750,"w":60,"h":75,"type":"tree"},{"x":300,"y":750,"w":60,"h":75,"type":"tree"},{"x":525,"y":600,"w":60,"h":75,"type":"tree"},{"x":525,"y":675,"w":60,"h":75,"type":"tree"},{"x":150,"y":675,"w":60,"h":75,"type":"tree"},{"x":150,"y":600,"w":60,"h":75,"type":"tree"},{"x":750,"y":900,"w":60,"h":75,"type":"tree"},{"x":825,"y":900,"w":60,"h":75,"type":"tree"},{"x":900,"y":900,"w":60,"h":75,"type":"tree"},{"x":975,"y":900,"w":60,"h":75,"type":"tree"},{"x":1050,"y":900,"w":60,"h":75,"type":"tree"},{"x":1125,"y":900,"w":60,"h":75,"type":"tree"},{"x":1200,"y":900,"w":60,"h":75,"type":"tree"},{"x":1275,"y":900,"w":60,"h":75,"type":"tree"},{"x":1350,"y":900,"w":60,"h":75,"type":"tree"},{"x":1350,"y":825,"w":60,"h":75,"type":"tree"},{"x":1350,"y":750,"w":60,"h":75,"type":"tree"},{"x":1350,"y":675,"w":60,"h":75,"type":"tree"},{"x":1350,"y":600,"w":60,"h":75,"type":"tree"},{"x":1350,"y":525,"w":60,"h":75,"type":"tree"},{"x":1350,"y":450,"w":60,"h":75,"type":"tree"},{"x":1275,"y":450,"w":60,"h":75,"type":"tree"},{"x":1200,"y":450,"w":60,"h":75,"type":"tree"},{"x":1125,"y":450,"w":60,"h":75,"type":"tree"},{"x":1050,"y":450,"w":60,"h":75,"type":"tree"},{"x":900,"y":450,"w":60,"h":75,"type":"tree"},{"x":825,"y":450,"w":60,"h":75,"type":"tree"},{"x":750,"y":450,"w":60,"h":75,"type":"tree"},{"x":975,"y":750,"w":60,"h":75,"type":"tree"},{"x":1050,"y":750,"w":60,"h":75,"type":"tree"},{"x":1125,"y":750,"w":60,"h":75,"type":"tree"},{"x":1200,"y":750,"w":60,"h":75,"type":"tree"},{"x":1200,"y":675,"w":60,"h":75,"type":"tree"},{"x":1200,"y":600,"w":60,"h":75,"type":"tree"},{"x":900,"y":750,"w":60,"h":75,"type":"tree"},{"x":1350,"y":375,"w":60,"h":75,"type":"tree"},{"x":1350,"y":225,"w":60,"h":75,"type":"tree"},{"x":1350,"y":300,"w":60,"h":75,"type":"tree"},{"x":1350,"y":150,"w":60,"h":75,"type":"tree"},{"x":1350,"y":75,"w":60,"h":75,"type":"tree"},{"x":1350,"y":0,"w":60,"h":75,"type":"tree"},{"x":1275,"y":0,"w":60,"h":75,"type":"tree"},{"x":1200,"y":0,"w":60,"h":75,"type":"tree"},{"x":1125,"y":0,"w":60,"h":75,"type":"tree"},{"x":1050,"y":0,"w":60,"h":75,"type":"tree"},{"x":975,"y":0,"w":60,"h":75,"type":"tree"},{"x":900,"y":0,"w":60,"h":75,"type":"tree"},{"x":825,"y":0,"w":60,"h":75,"type":"tree"},{"x":750,"y":0,"w":60,"h":75,"type":"tree"},{"x":450,"y":150,"w":60,"h":75,"type":"tree"},{"x":1125,"y":75,"w":60,"h":75,"type":"tree"},{"x":1125,"y":150,"w":60,"h":75,"type":"tree"},{"x":1125,"y":225,"w":60,"h":75,"type":"tree"},{"x":1200,"y":225,"w":60,"h":75,"type":"tree"},{"x":825,"y":375,"w":60,"h":75,"type":"tree"},{"x":825,"y":300,"w":60,"h":75,"type":"tree"},{"x":1125,"y":375,"w":60,"h":75,"type":"tree"},{"x":1203,"y":86,"w":40,"h":40,"type":"TreasureChest"},{"x":1275,"y":88,"w":40,"h":40,"type":"TreasureChest"},{"x":755,"y":392,"w":40,"h":40,"type":"TreasureChest"},{"x":1277,"y":828,"w":40,"h":40,"type":"TreasureChest"},{"x":78,"y":694,"w":40,"h":40,"type":"TreasureChest"},{"x":88,"y":843,"w":40,"h":40,"type":"TreasureChest"},{"x":0,"y":0,"w":60,"h":75,"type":"tree"},{"x":0,"y":525,"w":60,"h":75,"type":"tree"},{"x":84,"y":389,"w":40,"h":40,"type":"TreasureChest"},{"x":603,"y":89,"w":40,"h":40,"type":"TreasureChest"}]}